docchat/__init__.py
docchat/chat_engine.py
docchat-0.1.2.dist-info/LICENSE
docchat-0.1.2.dist-info/METADATA
docchat-0.1.2.dist-info/WHEEL
docchat-0.1.2.dist-info/RECORD
