Metadata-Version: 2.1
Name: docchat
Version: 0.1.2
Summary: 
Author: Patrik Larsson
Author-email: patrik@backyardml.se
Requires-Python: >=3.11,<4.0
Classifier: Programming Language :: Python :: 3
Classifier: Programming Language :: Python :: 3.11
Requires-Dist: chromadb (>=0.4.14,<0.5.0)
Requires-Dist: gradio (>=3.47.1,<4.0.0)
Requires-Dist: jupyter (>=1.0.0,<2.0.0)
Requires-Dist: langchain (>=0.0.312,<0.0.313)
Requires-Dist: openai (>=0.28.1,<0.29.0)
Requires-Dist: pypdf (>=3.16.4,<4.0.0)
Requires-Dist: tiktoken (>=0.5.1,<0.6.0)
Requires-Dist: unstructured[local-inference] (>=0.10.21,<0.11.0)
